<?xml version="1.0" encoding="UTF-8"?>
<info>
  <body>
    <div xml:id="pg-b1q1">
      <div xml:id="pg-b1q1-Dd1e3724">
        <head xml:id="pg-b1q1-Hd1e3726">Circa textum</head>
        <p xml:id="pgb1q1-cadanl"></p>
        <p xml:id="pgb1q1-ppdlde"></p>
        <p xml:id="pgb1q1-ppddis"></p>
        <p xml:id="pgb1q1-tssiqp"></p>
        <p xml:id="pgb1q1-sepicl"></p>
        <p xml:id="pgb1q1-tsqigp"></p>
        <p xml:id="pgb1q1-isvioa"></p>
        <p xml:id="pgb1q1-iapipv"></p>
      </div>
      <div xml:id="pg-b1q1-Dd1e3922"> 
        <head xml:id="pg-b1q1-Hd1e3924">
          Quaestio</head>
        <div xml:id="pg-b1q1-Dd1e3928">
          <head xml:id="pg-b1q1-Hd1e3930">
            Rationes principales</head> 
          <p xml:id="pgb1q1-uqvovs"></p>
          <p xml:id="pgb1q1-qspali"></p>
          <p xml:id="pgb1q1-shdsam">
            <assertions>
              <assertion property="isRelatedTo" target="http://scta.info/resource/jhbl1q2-d1e3581"/>
              <assertion property="isRelatedTo" target="http://scta.info/resource/jhbl1q2-d1e3593"/>
              <assertion property="isRelatedTo" target="http://scta.info/resource/jhbl1q2-tqdiqf"/>
            </assertions>
          </p> 
          <p xml:id="pgb1q1-tsqpap"></p>
          <p xml:id="pgb1q1-qvprit"></p>
          <p xml:id="pgb1q1-ioeqqv">
            <assertions>
              
              <assertion property="isRelatedTo" target="http://scta.info/resource/jhbl1q2-d1e3960"/>
              <assertion property="isRelatedTo" target="http://scta.info/resource/jhbl1q2-d1e3984"/>
              <assertion property="isRelatedTo" target="http://scta.info/resource/jhbl1q2-d1e4012"/>
              

              <assertion property="isRelatedTo" target="http://scta.info/resource/jhbl1q2-d1e4159"/>
              
            </assertions>
          </p>
        </div>
        <div xml:id="pg-b1q1-Dd1e4089">
          <head xml:id="pg-b1q1-Hd1e4091">Prima Conclusio</head>
          
          <p xml:id="pgb1q1-pclecv"></p>

          <p xml:id="pgb1q1-pcqnet"></p>
          
          
            
          <p xml:id="pgb1q1-scqeeh"></p> 
          
          <p xml:id="pgb1q1-tcqdia"></p>
        </div>
        <div xml:id="pg-b1q1-Dd1e4123">
          <head xml:id="pg-b1q1-Hd1e4125">Secunda Conclusio</head>
          <p xml:id="pgb1q1-scqsot"></p>
          
          <p xml:id="pgb1q1-pcqoss"></p>
          
          <p xml:id="pgb1q1-scqste"></p> 
          
          <p xml:id="pgb1q1-tcqvne"></p> 
        </div> 
        <div xml:id="pg-b1q1-Dd1e4151"> 
          <head xml:id="pg-b1q1-Hd1e4153">Tertio Conclusio</head>
          <p xml:id="pgb1q1-tclsie"></p> 
          <p xml:id="pgb1q1-pcpiss"></p> 
          <p xml:id="pgb1q1-scmiss"></p>
          <p xml:id="pgb1q1-tchnqv"></p>
          <p xml:id="pgb1q1-cpceia"></p>
          <p xml:id="pgb1q1-ssqsqp"></p>
          <p xml:id="pgb1q1-tpaeca"></p>
          <p xml:id="pgb1q1-qsiepm"></p>
          <p xml:id="pgb1q1-qcstss"></p>
          <p xml:id="pgb1q1-sccqrd"></p>
          <p xml:id="pgb1q1-scsons"></p>
          <p xml:id="pgb1q1-occrea"></p>
          <p xml:id="pgb1q1-nctiec"></p>
          <p xml:id="pgb1q1-dstogd"></p>
          <p xml:id="pgb1q1-unlfdm"></p>
        </div>
        <div xml:id="pg-b1q1-Dd1e1073">
          <head xml:id="pg-b1q1-Hd1e1075">Responses</head>
          <p xml:id="pgb1q1-arasap"></p>
          <p xml:id="pgb1q1-ascddt"></p> 
          <p xml:id="pgb1q1-atnepr"></p>
          <p xml:id="pgb1q1-aqnnmp"></p>
          <p xml:id="pgb1q1-aqcssa"></p>
          <p xml:id="pgb1q1-asdqas"></p>
          <p xml:id="pgb1q1-asqqpf"></p>
          <p xml:id="pgb1q1-aodsht"></p>
          <p xml:id="pgb1q1-aanpap"></p>
          <p xml:id="pgb1q1-aanafi"></p>
          <p xml:id="pgb1q1-aunqev"></p>
          <p xml:id="pgb1q1-aprpqq"></p>
          <p xml:id="pgb1q1-aaqinc">
            <assertions>
              <assertion property="isRelatedTo" target="http://scta.info/resource/jhbl1q2-d1e9659"/>
            </assertions>
          </p>
          <p xml:id="pgb1q1-aacpsp"></p>
          <p xml:id="pgb1q1-aupqef"></p>
          <p xml:id="pg-b1q1-d1e1266"/><!-- new 1 -->
        </div>
      </div>
    </div>
  </body>
</info>